funcalc/__init__.py
funcalc/calc.py
funcalc-0.1.0.dist-info/METADATA
funcalc-0.1.0.dist-info/WHEEL
funcalc-0.1.0.dist-info/RECORD
