Metadata-Version: 2.3
Name: funcalc
Version: 0.1.0
Summary: Calculator
Requires-Python: >=3.8
